odoo/addons/community_maps/__init__.py
odoo/addons/community_maps/__manifest__.py
odoo/addons/community_maps/controllers/__init__.py
odoo/addons/community_maps/controllers/cm_map_controller.py
odoo/addons/community_maps/controllers/cm_map_private_controller.py
odoo/addons/community_maps/controllers/cm_submission_transfer_controller.py
odoo/addons/community_maps/data/collect_place_submission_email_template.xml
odoo/addons/community_maps/data/ir_cron_submission_transfer.xml
odoo/addons/community_maps/models/__init__.py
odoo/addons/community_maps/models/cm_button_color_config.py
odoo/addons/community_maps/models/cm_crowdfunding_notification.py
odoo/addons/community_maps/models/cm_crowdfunding_notification_request.py
odoo/addons/community_maps/models/cm_external_id_mixin.py
odoo/addons/community_maps/models/cm_filter.py
odoo/addons/community_maps/models/cm_filter_group.py
odoo/addons/community_maps/models/cm_form_model.py
odoo/addons/community_maps/models/cm_form_submission.py
odoo/addons/community_maps/models/cm_form_submission_metadata.py
odoo/addons/community_maps/models/cm_form_submission_transfer_request.py
odoo/addons/community_maps/models/cm_map.py
odoo/addons/community_maps/models/cm_map_colorschema.py
odoo/addons/community_maps/models/cm_map_social_item.py
odoo/addons/community_maps/models/cm_partner.py
odoo/addons/community_maps/models/cm_place.py
odoo/addons/community_maps/models/cm_place_category.py
odoo/addons/community_maps/models/cm_place_child.py
odoo/addons/community_maps/models/cm_place_external_link.py
odoo/addons/community_maps/models/cm_place_image.py
odoo/addons/community_maps/models/cm_place_presenter_metadata.py
odoo/addons/community_maps/models/cm_presenter_model.py
odoo/addons/community_maps/models/cm_slug_id_mixin.py
odoo/addons/community_maps/models/cm_utils.py
odoo/addons/community_maps/security/ir.model.access.csv
odoo/addons/community_maps/security/res_groups.xml
odoo/addons/community_maps/security/rules.xml
odoo_addon_community_maps-16.0.2.0.8.dist-info/METADATA
odoo_addon_community_maps-16.0.2.0.8.dist-info/WHEEL
odoo_addon_community_maps-16.0.2.0.8.dist-info/top_level.txt
odoo_addon_community_maps-16.0.2.0.8.dist-info/RECORD
