Metadata-Version: 2.1
Name: odoo-addon-community_maps
Version: 16.0.2.0.8
Requires-Python: >=3.10
Requires-Dist: odoo-addon-base_rest>=16.0dev,<16.1dev
Requires-Dist: odoo-addon-metadata>=16.0dev,<16.1dev
Requires-Dist: odoo-addon-queue_job>=16.0dev,<16.1dev
Requires-Dist: odoo>=16.0a,<16.1dev
Requires-Dist: python-slugify
Summary: Module to create and manage your map visualizations into a website
Home-page: https://gitlab.com/somitcoop/erp-research/community-maps
Author: Community Maps
Classifier: Programming Language :: Python
Classifier: Framework :: Odoo
Classifier: Framework :: Odoo :: 16.0
